traceid/__init__.py
traceid/logging.py
traceid/py.typed
traceid/traceid.py
traceid-1.1.1.dist-info/LICENSE
traceid-1.1.1.dist-info/METADATA
traceid-1.1.1.dist-info/WHEEL
traceid-1.1.1.dist-info/RECORD
