Metadata-Version: 2.1
Name: traceid
Version: 1.1.1
Summary: TraceId is a trace ID generator based on Python contextvars. It automatically passes the trace ID in asynchronous tasks, enabling cross-coroutine tracing.
License: BSD 3-Clause
Author: Yibu Ma
Requires-Python: >=3.11,<4.0
Classifier: License :: Other/Proprietary License
Classifier: Programming Language :: Python :: 3
Classifier: Programming Language :: Python :: 3.11
Classifier: Programming Language :: Python :: 3.12
